csv_data_generator-0.0.5.dist-info/METADATA
csv_data_generator-0.0.5.dist-info/WHEEL
csv_data_generator-0.0.5.dist-info/entry_points.txt
csv_data_generator-0.0.5.dist-info/licenses/LICENSE
csv_data_generator/.coverage
csv_data_generator/__init__.py
csv_data_generator/__main__.py
csv_data_generator/cli.py
csv_data_generator/csv_generator.py
csv_data_generator/dict/words.txt
csv_data_generator-0.0.5.dist-info/RECORD
