Metadata-Version: 2.1
Name: csv-data-generator
Version: 0.0.5
Summary: A CSV data generator
Author-Email: Bruno Fagundez <bfagundez@gmail.com>
License:  GNU GENERAL PUBLIC LICENSE
Classifier: Development Status :: 3 - Alpha
Classifier: Programming Language :: Python
Classifier: Programming Language :: Python :: 3
Classifier: License :: OSI Approved :: MIT License
Classifier: Operating System :: OS Independent
Project-URL: Homepage, https://github.com/bfagundez/csv_data_generator
Project-URL: Bug tracker, https://github.com/bfagundez/csv_data_generator/issues
Requires-Python: >=3.7
Requires-Dist: click
Requires-Dist: yapf; extra == "dev"
Requires-Dist: pylint; extra == "dev"
Requires-Dist: pytest; extra == "test"
Requires-Dist: pytest-cov; extra == "test"
Provides-Extra: dev
Provides-Extra: test
